Metadata-Version: 2.1
Name: streamz-opencv
Version: 0.1.1
Summary: Provide opencv sources to streamz
Home-page: https://github.com/ingwinlu/streamz-opencv
Author: Lukas Winkler
Author-email: <derwinlu@gmail.com>
License: MIT
Keywords: streamz opencv
Platform: UNKNOWN
Classifier: License :: OSI Approved :: MIT License
Classifier: Programming Language :: Python :: 3
Classifier: Programming Language :: Python :: 3.7
Classifier: Programming Language :: Python :: 3.8
